aiohoripy/__init__.py
aiohoripy/api.py
aiohoripy/http.py
aiohoripy-0.0.2.dist-info/LICENSE
aiohoripy-0.0.2.dist-info/METADATA
aiohoripy-0.0.2.dist-info/WHEEL
aiohoripy-0.0.2.dist-info/top_level.txt
aiohoripy-0.0.2.dist-info/RECORD
