Metadata-Version: 2.1
Name: aiohoripy
Version: 0.0.2
Summary: An asynchronous Python Wrapper for Hori-API
Home-page: https://github.com/lvlahraam/aiohoripy
Author: lvlahraam
License: MIT
Keywords: python,api,discord,http,anime,hori
Platform: UNKNOWN
Classifier: Development Status :: 5 - Production/Stable
Classifier: License :: OSI Approved :: MIT License
Classifier: Intended Audience :: Developers
Classifier: Natural Language :: English
Classifier: Operating System :: OS Independent
Classifier: Programming Language :: Python :: 3.8
Classifier: Programming Language :: Python :: 3.9
Classifier: Topic :: Internet
Classifier: Topic :: Internet :: WWW/HTTP
Classifier: Topic :: Internet :: WWW/HTTP :: HTTP Servers
Classifier: Topic :: Internet :: WWW/HTTP :: Session
Classifier: Topic :: Software Development :: Libraries
Classifier: Topic :: Software Development :: Libraries :: Python Modules
Classifier: Topic :: Utilities
Classifier: Typing :: Typed
Requires-Python: >=3.8.0
Requires-Dist: aiohttp
Requires-Dist: async-timeout
Requires-Dist: typing-extensions
Requires-Dist: multidict
Requires-Dist: attrs
Requires-Dist: yarl
Requires-Dist: chardet
